demyst/cli/command.py
demyst/cli/file_transfer.py
demyst/cli/pii.py
demyst/cli/util.py
demyst/cli/auth/command.py
demyst/cli/channel/command.py
demyst_cli-0.9.0.dist-info/METADATA
demyst_cli-0.9.0.dist-info/WHEEL
demyst_cli-0.9.0.dist-info/entry_points.txt
demyst_cli-0.9.0.dist-info/top_level.txt
demyst_cli-0.9.0.dist-info/RECORD
